appdirs.py
xdgappdirs.py
xdgappdirs-1.4.5.dist-info/LICENSE.txt
xdgappdirs-1.4.5.dist-info/METADATA
xdgappdirs-1.4.5.dist-info/WHEEL
xdgappdirs-1.4.5.dist-info/top_level.txt
xdgappdirs-1.4.5.dist-info/RECORD
