Metadata-Version: 2.1
Name: xdgappdirs
Version: 1.4.5
Summary: A small Python module for determining appropriate platform-specific dirs, e.g. a "user data dir".
Home-page: https://github.com/zmwangx/xdgappdirs
Author: Zhiming Wang
Author-email: i@zhimingwang.org
License: MIT
Keywords: application directory log cache user
Platform: UNKNOWN
Classifier: Development Status :: 5 - Production/Stable
Classifier: Intended Audience :: Developers
Classifier: License :: OSI Approved :: MIT License
Classifier: Operating System :: OS Independent
Classifier: Programming Language :: Python
Classifier: Programming Language :: Python :: 2
Classifier: Programming Language :: Python :: 2.7
Classifier: Programming Language :: Python :: 3
Classifier: Programming Language :: Python :: 3.4
Classifier: Programming Language :: Python :: 3.5
Classifier: Programming Language :: Python :: 3.6
Classifier: Programming Language :: Python :: 3.7
Classifier: Programming Language :: Python :: Implementation :: PyPy
Classifier: Programming Language :: Python :: Implementation :: CPython
Classifier: Topic :: Software Development :: Libraries :: Python Modules
